alquran/__init__.py
alquran/cli.py
alquran/config.py
alquran/core.py
alquran/hadits.py
alquran/surah.py
alquran/utils/version.py
alquran_cli-0.2.6.dist-info/LICENSE
alquran_cli-0.2.6.dist-info/METADATA
alquran_cli-0.2.6.dist-info/WHEEL
alquran_cli-0.2.6.dist-info/entry_points.txt
alquran_cli-0.2.6.dist-info/top_level.txt
alquran_cli-0.2.6.dist-info/RECORD
