Metadata-Version: 2.2
Name: alquran-cli
Version: 0.2.6
Summary: CLI untuk memberikan isi alquran dan hadits
Author-email: Anggi Ananda <anggiangga443@gmail.com>
License: MIT License
Project-URL: homepage, https://github.com/anggiAnand/alquran-cli.git
Project-URL: repository, https://github.com/anggiAnand/alquran-cli.git
Requires-Python: >=3.11
License-File: LICENSE
Requires-Dist: click>=8.1.8
Requires-Dist: requests>=2.32.3
Requires-Dist: httpx>=0.28.1
